findontime/__init__.py
findontime/__main__.py
findontime/configs.py
findontime/connectors.py
findontime/drones.py
findontime/insaflu_uploads.py
findontime/manager.py
findontime/plot_utils.py
findontime/plotting_from_all_reports.py
findontime/records.py
findontime/tables_post.py
findontime/upload_utils.py
findontime-0.2.71.dist-info/LICENSE
findontime-0.2.71.dist-info/METADATA
findontime-0.2.71.dist-info/WHEEL
findontime-0.2.71.dist-info/entry_points.txt
findontime-0.2.71.dist-info/RECORD
