Metadata-Version: 2.1
Name: findontime
Version: 0.2.71
Summary: A tool to upload Fastq files to the INSaFLU database and perform metagenomics pathogen detection
License: MIT
Author: SantosJGND
Author-email: dourado.jns@gmail.com
Requires-Python: >=3.9,<4.0
Classifier: License :: OSI Approved :: MIT License
Classifier: Programming Language :: Python :: 3
Classifier: Programming Language :: Python :: 3.9
Classifier: Programming Language :: Python :: 3.10
Classifier: Programming Language :: Python :: 3.11
Requires-Dist: Twisted (==16.7.0rc2)
Requires-Dist: dash-bootstrap-components (==1.4.1)
Requires-Dist: dataclasses (==0.6)
Requires-Dist: fastq-handler (>=0.2.0,<0.3.0)
Requires-Dist: natsort (==8.3.1)
Requires-Dist: paramiko (>=3.1.0,<4.0.0)
Requires-Dist: seaborn (==0.12.2)
Requires-Dist: sqlalchemy (==1.4.23)
Requires-Dist: xopen (==1.7.0)
Project-URL: homepage, https://github.com/INSaFLU/findONTime
